pirel/__init__.py
pirel/__main__.py
pirel/_cache.py
pirel/_guess.py
pirel/_utils.py
pirel/cli.py
pirel/logging.py
pirel/python_cli.py
pirel/releases.py
pirel-0.4.0.dist-info/METADATA
pirel-0.4.0.dist-info/WHEEL
pirel-0.4.0.dist-info/entry_points.txt
pirel-0.4.0.dist-info/licenses/LICENSE
pirel-0.4.0.dist-info/RECORD
