Metadata-Version: 2.4
Name: pirel
Version: 0.4.0
Summary: The Python release cycle in your terminal
Project-URL: Homepage, https://github.com/RafaelWO/pirel
Project-URL: Repository, https://github.com/RafaelWO/pirel
Project-URL: Issues, https://github.com/RafaelWO/pirel/issues
Project-URL: Changelog, https://github.com/RafaelWO/pirel/blob/main/CHANGELOG.md
Author-email: Rafael Weingartner-Ortner <weingartner.rafael@hotmail.com>
License: The MIT License (MIT)
License-File: LICENSE
Keywords: cli,python,releases
Classifier: Development Status :: 3 - Alpha
Classifier: Intended Audience :: Developers
Classifier: License :: OSI Approved :: MIT License
Classifier: Programming Language :: Python :: 3
Classifier: Programming Language :: Python :: 3.10
Classifier: Programming Language :: Python :: 3.11
Classifier: Programming Language :: Python :: 3.12
Classifier: Programming Language :: Python :: 3.13
Classifier: Programming Language :: Python :: 3.14
Classifier: Topic :: Software Development
Requires-Python: >=3.10
Requires-Dist: humanize>=4.10.0
Requires-Dist: platformdirs>=4.3.6
Requires-Dist: rich>=13.9.2
Requires-Dist: typer>=0.12.5
